pyzr/__init__.py
pyzr/alert.py
pyzr/phone.py
pyzr-0.0.4.dist-info/LICENSE
pyzr-0.0.4.dist-info/METADATA
pyzr-0.0.4.dist-info/WHEEL
pyzr-0.0.4.dist-info/top_level.txt
pyzr-0.0.4.dist-info/RECORD
