Metadata-Version: 2.1
Name: pyzr
Version: 0.0.4
Summary: A simple tools package
Author: guzhi
License: UNKNOWN
Platform: UNKNOWN
Classifier: Programming Language :: Python :: 3
Classifier: License :: OSI Approved :: MIT License
Classifier: Operating System :: OS Independent
Requires-Python: >=3.6
License-File: LICENSE
